{"bettergrblsupport": {"total": 146, "history": [{"date": "2025-06-14", "total": 149, "issues": {"open": 17, "closed": 79}}, {"date": "2025-06-15", "total": 152, "issues": {"open": 17, "closed": 79}}, {"date": "2025-06-16", "total": 156, "issues": {"open": 17, "closed": 79}}, {"date": "2025-06-17", "total": 158, "issues": {"open": 17, "closed": 79}}, {"date": "2025-06-18", "total": 158, "issues": {"open": 17, "closed": 79}}, {"date": "2025-06-19", "total": 159, "issues": {"open": 17, "closed": 79}}, {"date": "2025-06-20", "total": 154, "issues": {"open": 17, "closed": 79}}, {"date": "2025-06-21", "total": 153, "issues": {"open": 17, "closed": 79}}, {"date": "2025-06-22", "total": 155, "issues": {"open": 17, "closed": 79}}, {"date": "2025-06-23", "total": 156, "issues": {"open": 17, "closed": 79}}, {"date": "2025-06-24", "total": 160, "issues": {"open": 17, "closed": 79}}, {"date": "2025-06-25", "total": 158, "issues": {"open": 17, "closed": 79}}, {"date": "2025-06-26", "total": 158, "issues": {"open": 17, "closed": 79}}, {"date": "2025-06-27", "total": 158, "issues": {"open": 17, "closed": 79}}, {"date": "2025-06-28", "total": 154, "issues": {"open": 17, "closed": 79}}, {"date": "2025-06-29", "total": 153, "issues": {"open": 17, "closed": 79}}, {"date": "2025-06-30", "total": 154, "issues": {"open": 17, "closed": 79}}, {"date": "2025-07-01", "total": 150, "issues": {"open": 17, "closed": 79}}, {"date": "2025-07-02", "total": 149, "issues": {"open": 17, "closed": 79}}, {"date": "2025-07-03", "total": 151, "issues": {"open": 17, "closed": 79}}, {"date": "2025-07-04", "total": 149, "issues": {"open": 17, "closed": 79}}, {"date": "2025-07-05", "total": 147, "issues": {"open": 17, "closed": 79}}, {"date": "2025-07-06", "total": 145, "issues": {"open": 17, "closed": 79}}, {"date": "2025-07-07", "total": 143, "issues": {"open": 17, "closed": 79}}, {"date": "2025-07-08", "total": 139, "issues": {"open": 17, "closed": 79}}, {"date": "2025-07-09", "total": 142, "issues": {"open": 17, "closed": 79}}, {"date": "2025-07-10", "total": 142, "issues": {"open": 17, "closed": 79}}, {"date": "2025-07-11", "total": 143, "issues": {"open": 17, "closed": 79}}, {"date": "2025-07-12", "total": 145, "issues": {"open": 17, "closed": 79}}, {"date": "2025-07-13", "total": 146, "issues": {"open": 17, "closed": 79}}], "title": "Better Grbl Support"}, "ServoSpindle": {"total": 13, "history": [{"date": "2025-06-14", "total": 10, "issues": {"open": 0, "closed": 0}}, {"date": "2025-06-15", "total": 10, "issues": {"open": 0, "closed": 0}}, {"date": "2025-06-16", "total": 10, "issues": {"open": 0, "closed": 0}}, {"date": "2025-06-17", "total": 10, "issues": {"open": 0, "closed": 0}}, {"date": "2025-06-18", "total": 10, "issues": {"open": 0, "closed": 0}}, {"date": "2025-06-19", "total": 10, "issues": {"open": 0, "closed": 0}}, {"date": "2025-06-20", "total": 10, "issues": {"open": 0, "closed": 0}}, {"date": "2025-06-21", "total": 11, "issues": {"open": 0, "closed": 0}}, {"date": "2025-06-22", "total": 11, "issues": {"open": 0, "closed": 0}}, {"date": "2025-06-23", "total": 11, "issues": {"open": 0, "closed": 0}}, {"date": "2025-06-24", "total": 11, "issues": {"open": 0, "closed": 0}}, {"date": "2025-06-25", "total": 10, "issues": {"open": 0, "closed": 0}}, {"date": "2025-06-26", "total": 11, "issues": {"open": 0, "closed": 0}}, {"date": "2025-06-27", "total": 11, "issues": {"open": 0, "closed": 0}}, {"date": "2025-06-28", "total": 10, "issues": {"open": 0, "closed": 0}}, {"date": "2025-06-29", "total": 10, "issues": {"open": 0, "closed": 0}}, {"date": "2025-06-30", "total": 11, "issues": {"open": 0, "closed": 0}}, {"date": "2025-07-01", "total": 11, "issues": {"open": 0, "closed": 0}}, {"date": "2025-07-02", "total": 11, "issues": {"open": 0, "closed": 0}}, {"date": "2025-07-03", "total": 12, "issues": {"open": 0, "closed": 0}}, {"date": "2025-07-04", "total": 12, "issues": {"open": 0, "closed": 0}}, {"date": "2025-07-05", "total": 12, "issues": {"open": 0, "closed": 0}}, {"date": "2025-07-06", "total": 12, "issues": {"open": 0, "closed": 0}}, {"date": "2025-07-07", "total": 12, "issues": {"open": 0, "closed": 0}}, {"date": "2025-07-08", "total": 12, "issues": {"open": 0, "closed": 0}}, {"date": "2025-07-09", "total": 13, "issues": {"open": 0, "closed": 0}}, {"date": "2025-07-10", "total": 13, "issues": {"open": 0, "closed": 0}}, {"date": "2025-07-11", "total": 13, "issues": {"open": 0, "closed": 0}}, {"date": "2025-07-12", "total": 13, "issues": {"open": 0, "closed": 0}}, {"date": "2025-07-13", "total": 13, "issues": {"open": 0, "closed": 0}}], "title": "Servo Spindle for GRBL CNC"}, "systemcommandeditor": {"total": 646, "history": [{"date": "2025-06-14", "total": 666, "issues": {"open": 1, "closed": 1}}, {"date": "2025-06-15", "total": 674, "issues": {"open": 1, "closed": 1}}, {"date": "2025-06-16", "total": 675, "issues": {"open": 1, "closed": 1}}, {"date": "2025-06-17", "total": 677, "issues": {"open": 1, "closed": 1}}, {"date": "2025-06-18", "total": 676, "issues": {"open": 1, "closed": 1}}, {"date": "2025-06-19", "total": 676, "issues": {"open": 1, "closed": 1}}, {"date": "2025-06-20", "total": 675, "issues": {"open": 1, "closed": 1}}, {"date": "2025-06-21", "total": 675, "issues": {"open": 1, "closed": 1}}, {"date": "2025-06-22", "total": 672, "issues": {"open": 1, "closed": 1}}, {"date": "2025-06-23", "total": 677, "issues": {"open": 1, "closed": 1}}, {"date": "2025-06-24", "total": 677, "issues": {"open": 1, "closed": 1}}, {"date": "2025-06-25", "total": 673, "issues": {"open": 1, "closed": 1}}, {"date": "2025-06-26", "total": 670, "issues": {"open": 1, "closed": 1}}, {"date": "2025-06-27", "total": 670, "issues": {"open": 1, "closed": 1}}, {"date": "2025-06-28", "total": 671, "issues": {"open": 1, "closed": 1}}, {"date": "2025-06-29", "total": 666, "issues": {"open": 1, "closed": 1}}, {"date": "2025-06-30", "total": 664, "issues": {"open": 1, "closed": 1}}, {"date": "2025-07-01", "total": 662, "issues": {"open": 1, "closed": 1}}, {"date": "2025-07-02", "total": 654, "issues": {"open": 1, "closed": 1}}, {"date": "2025-07-03", "total": 651, "issues": {"open": 1, "closed": 1}}, {"date": "2025-07-04", "total": 655, "issues": {"open": 1, "closed": 1}}, {"date": "2025-07-05", "total": 660, "issues": {"open": 1, "closed": 1}}, {"date": "2025-07-06", "total": 659, "issues": {"open": 1, "closed": 1}}, {"date": "2025-07-07", "total": 655, "issues": {"open": 1, "closed": 1}}, {"date": "2025-07-08", "total": 652, "issues": {"open": 1, "closed": 1}}, {"date": "2025-07-09", "total": 652, "issues": {"open": 1, "closed": 1}}, {"date": "2025-07-10", "total": 650, "issues": {"open": 1, "closed": 1}}, {"date": "2025-07-11", "total": 653, "issues": {"open": 1, "closed": 1}}, {"date": "2025-07-12", "total": 651, "issues": {"open": 1, "closed": 1}}, {"date": "2025-07-13", "total": 646, "issues": {"open": 1, "closed": 1}}], "title": "System Command Editor"}, "mqttchambertemperature": {"total": 45, "history": [{"date": "2025-06-14", "total": 48, "issues": {"open": 3, "closed": 2}}, {"date": "2025-06-15", "total": 49, "issues": {"open": 3, "closed": 2}}, {"date": "2025-06-16", "total": 47, "issues": {"open": 3, "closed": 2}}, {"date": "2025-06-17", "total": 46, "issues": {"open": 3, "closed": 2}}, {"date": "2025-06-18", "total": 46, "issues": {"open": 3, "closed": 2}}, {"date": "2025-06-19", "total": 47, "issues": {"open": 3, "closed": 2}}, {"date": "2025-06-20", "total": 47, "issues": {"open": 3, "closed": 2}}, {"date": "2025-06-21", "total": 47, "issues": {"open": 3, "closed": 2}}, {"date": "2025-06-22", "total": 47, "issues": {"open": 3, "closed": 2}}, {"date": "2025-06-23", "total": 49, "issues": {"open": 3, "closed": 2}}, {"date": "2025-06-24", "total": 49, "issues": {"open": 3, "closed": 2}}, {"date": "2025-06-25", "total": 48, "issues": {"open": 3, "closed": 2}}, {"date": "2025-06-26", "total": 48, "issues": {"open": 3, "closed": 2}}, {"date": "2025-06-27", "total": 48, "issues": {"open": 3, "closed": 2}}, {"date": "2025-06-28", "total": 48, "issues": {"open": 3, "closed": 2}}, {"date": "2025-06-29", "total": 48, "issues": {"open": 3, "closed": 2}}, {"date": "2025-06-30", "total": 48, "issues": {"open": 3, "closed": 2}}, {"date": "2025-07-01", "total": 47, "issues": {"open": 3, "closed": 2}}, {"date": "2025-07-02", "total": 47, "issues": {"open": 3, "closed": 2}}, {"date": "2025-07-03", "total": 48, "issues": {"open": 3, "closed": 2}}, {"date": "2025-07-04", "total": 47, "issues": {"open": 3, "closed": 2}}, {"date": "2025-07-05", "total": 48, "issues": {"open": 3, "closed": 2}}, {"date": "2025-07-06", "total": 48, "issues": {"open": 3, "closed": 2}}, {"date": "2025-07-07", "total": 48, "issues": {"open": 3, "closed": 2}}, {"date": "2025-07-08", "total": 47, "issues": {"open": 3, "closed": 2}}, {"date": "2025-07-09", "total": 47, "issues": {"open": 3, "closed": 2}}, {"date": "2025-07-10", "total": 46, "issues": {"open": 3, "closed": 2}}, {"date": "2025-07-11", "total": 45, "issues": {"open": 3, "closed": 2}}, {"date": "2025-07-12", "total": 45, "issues": {"open": 3, "closed": 2}}, {"date": "2025-07-13", "total": 45, "issues": {"open": 3, "closed": 2}}], "title": "MQTT Chamber Temperature"}}